{
  "kind": "collectionType",
  "collectionName": "posts",
  "info": {
    "singularName": "post",
    "pluralName": "posts",
    "displayName": "Post",
    "description": ""
  },
  "options": {
    "draftAndPublish": false
  },
  "pluginOptions": {},
  "attributes": {
    "content": {
      "type": "text"
    },
    "user": {
      "type": "relation",
      "relation": "manyToOne",
      "target": "plugin::users-permissions.user",
      "inversedBy": "posts"
    },
    "likes": {
      "type": "relation",
      "relation": "oneToMany",
      "target": "plugin::users-permissions.user"
    }
  }
}
